{
  "evictions": [],
  "metadata": {
    "generated_at": "2026-04-26T18:01:33Z",
    "count": 0,
    "global_metrics": {
      "total_runs": 14,
      "total_run_time_seconds": 2514.1407465934753,
      "total_repo_updates": 917,
      "previous_total_buckets": 759,
      "previous_total_recipes": 116778,
      "bucket_velocity": 52,
      "recipe_velocity": 667,
      "total_evictions": 0,
      "total_api_retries": 0,
      "last_run_discover_time": 2.323791742324829,
      "last_run_update_time": 639.76904129982,
      "ecosystem_reliability": 89.4,
      "cache_size_mb": 8.574073791503906,
      "total_unique_recipes": 29910,
      "auto_update_percentage": 85.5,
      "official_recipes": 41990,
      "community_recipes": 74788,
      "stale_buckets": 232,
      "shovel_buckets": 24,
      "scoop_buckets": 735
    }
  }
}
