{
  "trending": [
    {
      "name": "scoop-bucket",
      "full_name": "qyurila/scoop-bucket",
      "git_url": "https://github.com/qyurila/scoop-bucket.git",
      "html_url": "https://github.com/qyurila/scoop-bucket",
      "score": 1.0,
      "default_branch": "master",
      "topics": [],
      "last_checked": "2026-05-07T14:05:32Z",
      "pushed_at": "2026-05-06T04:09:29Z",
      "archived": false,
      "disabled": false,
      "entries": [
        "bucket/hackbgrt.json",
        "bucket/tagstudio.json",
        "bucket/wavetone.json",
        "bucket/vocalshifter-le.json",
        "bucket/dnvm.json",
        "bucket/ticktick.json"
      ],
      "checkver_count": 6,
      "consecutive_failures": 20,
      "probe_success_rate": 1.0,
      "valid_probes": 3,
      "total_probes": 3,
      "unique_count": 6,
      "uniqueness_ratio": 1.0,
      "auto_update_percentage": 100.0,
      "final_score": 61.6886522358297,
      "current_rank": 376,
      "rank_velocity": 63,
      "previous_rank": 376,
      "is_scoop_official": false,
      "is_scoop_known": false,
      "is_shovel_official": false,
      "is_shovel_known": false
    },
    {
      "name": "unity3d",
      "full_name": "tree-s/unity3d",
      "git_url": "https://github.com/tree-s/unity3d.git",
      "html_url": "https://github.com/tree-s/unity3d",
      "score": 1.0,
      "default_branch": "master",
      "topics": [
        "scoop",
        "scoop-bucket"
      ],
      "last_checked": "2026-05-07T14:05:48Z",
      "pushed_at": "2026-04-29T10:27:18Z",
      "archived": false,
      "disabled": false,
      "entries": [
        "bucket/unity2020lts.json",
        "bucket/unity2018lts.json",
        "bucket/unity2022lts.json",
        "bucket/unity2017lts.json",
        "bucket/unity2019lts.json",
        "bucket/unity2023tech.json",
        "bucket/unity6000lts.json",
        "bucket/unity2021lts.json"
      ],
      "checkver_count": 8,
      "consecutive_failures": 18,
      "probe_success_rate": 1.0,
      "valid_probes": 3,
      "total_probes": 3,
      "unique_count": 8,
      "uniqueness_ratio": 1.0,
      "auto_update_percentage": 100.0,
      "final_score": 69.45836866004329,
      "current_rank": 328,
      "rank_velocity": 58,
      "previous_rank": 328,
      "is_scoop_official": false,
      "is_scoop_known": false,
      "is_shovel_official": false,
      "is_shovel_known": false
    },
    {
      "name": "f1bsh",
      "full_name": "f1a3h/f1bsh",
      "git_url": "https://github.com/f1a3h/f1bsh.git",
      "html_url": "https://github.com/f1a3h/f1bsh",
      "score": 1.0,
      "default_branch": "main",
      "topics": [],
      "last_checked": "2026-05-07T14:05:44Z",
      "pushed_at": "2026-05-06T04:09:28Z",
      "archived": false,
      "disabled": false,
      "entries": [
        "bucket/vocabsieve.json",
        "bucket/neteasemusic.json",
        "bucket/remnote.json",
        "bucket/dida365.json",
        "bucket/zen-browser.json",
        "bucket/quicker.json",
        "bucket/vnite.json",
        "bucket/remnote-beta.json",
        "bucket/pixpin.json"
      ],
      "checkver_count": 8,
      "consecutive_failures": 31,
      "probe_success_rate": 1.0,
      "valid_probes": 3,
      "total_probes": 3,
      "unique_count": 8,
      "uniqueness_ratio": 0.8888888888888888,
      "auto_update_percentage": 88.89,
      "final_score": 73.03877639491068,
      "current_rank": 321,
      "rank_velocity": 44,
      "previous_rank": 321,
      "is_scoop_official": false,
      "is_scoop_known": false,
      "is_shovel_official": false,
      "is_shovel_known": false
    },
    {
      "name": "scoop_bucket_misty",
      "full_name": "NyaMisty/scoop_bucket_misty",
      "git_url": "https://github.com/NyaMisty/scoop_bucket_misty.git",
      "html_url": "https://github.com/NyaMisty/scoop_bucket_misty",
      "score": 1.0,
      "default_branch": "master",
      "topics": [],
      "last_checked": "2026-05-07T14:05:35Z",
      "pushed_at": "2026-05-06T16:00:20Z",
      "archived": false,
      "disabled": false,
      "entries": [
        "bucket/gostv3.json",
        "bucket/fclone.json",
        "bucket/UAssetGUI.json",
        "bucket/AssetStudioMod.json",
        "bucket/chfs.json",
        "bucket/tun2proxy.json",
        "bucket/wireshark-nightly.json",
        "bucket/libimobiledevice-nightly.json",
        "bucket/inspectdev.json",
        "bucket/jclasslib.json",
        "bucket/rizin-nightly.json",
        "bucket/dnSpyEx-nightly.json",
        "bucket/dnSpyEx.json"
      ],
      "checkver_count": 13,
      "consecutive_failures": 37,
      "probe_success_rate": 1.0,
      "valid_probes": 3,
      "total_probes": 3,
      "unique_count": 12,
      "uniqueness_ratio": 0.9230769230769231,
      "auto_update_percentage": 100.0,
      "final_score": 86.08585994422887,
      "current_rank": 262,
      "rank_velocity": 42,
      "previous_rank": 262,
      "is_scoop_official": false,
      "is_scoop_known": false,
      "is_shovel_official": false,
      "is_shovel_known": false
    },
    {
      "name": "scoop-jiepot",
      "full_name": "jeangod/scoop-jiepot",
      "git_url": "https://github.com/jeangod/scoop-jiepot.git",
      "html_url": "https://github.com/jeangod/scoop-jiepot",
      "score": 1.0,
      "default_branch": "master",
      "topics": [
        "scoop-buckets"
      ],
      "last_checked": "2026-05-07T14:05:49Z",
      "pushed_at": "2026-05-01T09:59:42Z",
      "archived": false,
      "disabled": false,
      "entries": [
        "bucket/flymd.json",
        "bucket/flclash.json",
        "bucket/q-dir.json",
        "bucket/winscp.json",
        "bucket/es-king.json",
        "bucket/xdown.json",
        "bucket/lx-music.json",
        "bucket/pixpin.json",
        "bucket/dbeaver-ue.json",
        "bucket/thunder-professional.json"
      ],
      "checkver_count": 10,
      "consecutive_failures": 18,
      "probe_success_rate": 1.0,
      "valid_probes": 3,
      "total_probes": 3,
      "unique_count": 7,
      "uniqueness_ratio": 0.7,
      "auto_update_percentage": 100.0,
      "final_score": 76.46842909197557,
      "current_rank": 304,
      "rank_velocity": 37,
      "previous_rank": 304,
      "is_scoop_official": false,
      "is_scoop_known": false,
      "is_shovel_official": false,
      "is_shovel_known": false
    }
  ],
  "metadata": {
    "generated_at": "2026-05-07T14:31:48Z",
    "count": 5,
    "global_metrics": {
      "total_runs": 254,
      "total_run_time_seconds": 42045.603430747986,
      "total_repo_updates": 15761,
      "previous_total_buckets": 1257,
      "previous_total_recipes": 127748,
      "bucket_velocity": 0,
      "recipe_velocity": 0,
      "total_evictions": 0,
      "total_api_retries": 0,
      "last_run_discover_time": 4.073305606842041,
      "last_run_update_time": 614.205150604248,
      "ecosystem_reliability": 88.9,
      "cache_size_mb": 9.57336711883545,
      "total_unique_recipes": 31039,
      "auto_update_percentage": 85.36,
      "official_recipes": 48436,
      "community_recipes": 79312,
      "stale_buckets": 433,
      "shovel_buckets": 25,
      "scoop_buckets": 1232
    }
  }
}
