{
  "trending": [
    {
      "name": "scoop",
      "full_name": "SnowSquire/scoop",
      "git_url": "https://github.com/SnowSquire/scoop.git",
      "html_url": "https://github.com/SnowSquire/scoop",
      "score": 1.0,
      "default_branch": "main",
      "topics": [
        "scoop-bucket"
      ],
      "last_checked": "2026-04-29T19:55:45Z",
      "pushed_at": "2026-04-28T09:08:46Z",
      "archived": false,
      "disabled": false,
      "entries": [
        "bucket/vic3-tiger.json",
        "bucket/irony-mod-manager.json",
        "bucket/imperator-tiger.json",
        "bucket/ck3-tiger.json",
        "bucket/xwin.json"
      ],
      "checkver_count": 5,
      "consecutive_failures": 4,
      "probe_success_rate": 1.0,
      "valid_probes": 3,
      "total_probes": 3,
      "unique_count": 5,
      "uniqueness_ratio": 1.0,
      "auto_update_percentage": 100.0,
      "final_score": 57.376392038420825,
      "current_rank": 391,
      "rank_velocity": 59,
      "previous_rank": 391,
      "is_scoop_official": false,
      "is_scoop_known": false,
      "is_shovel_official": false,
      "is_shovel_known": false
    },
    {
      "name": "ScoopMirrored",
      "full_name": "amorphobia/ScoopMirrored",
      "git_url": "https://github.com/amorphobia/ScoopMirrored.git",
      "html_url": "https://github.com/amorphobia/ScoopMirrored",
      "score": 1.0,
      "default_branch": "master",
      "topics": [
        "scoop-bucket"
      ],
      "last_checked": "2026-04-29T19:55:48Z",
      "pushed_at": "2026-04-28T14:44:08Z",
      "archived": false,
      "disabled": false,
      "entries": [
        "bucket/rustdesk.json",
        "bucket/cmder-full.json",
        "bucket/llvm.json",
        "bucket/etcher.json",
        "bucket/cmder.json",
        "bucket/deno.json",
        "bucket/rufus.json",
        "bucket/ventoy.json",
        "bucket/nanazip.json",
        "bucket/atom.json",
        "bucket/putty.json",
        "bucket/git.json",
        "bucket/pwsh.json",
        "bucket/uv.json",
        "bucket/7zip.json",
        "bucket/vscodium.json",
        "bucket/powertoys.json",
        "bucket/stellarium.json",
        "bucket/gitea.json"
      ],
      "checkver_count": 19,
      "consecutive_failures": 7,
      "probe_success_rate": 1.0,
      "valid_probes": 3,
      "total_probes": 3,
      "unique_count": 0,
      "uniqueness_ratio": 0.0,
      "auto_update_percentage": 100.0,
      "final_score": 103.43598410330986,
      "current_rank": 214,
      "rank_velocity": 24,
      "previous_rank": 214,
      "is_scoop_official": false,
      "is_scoop_known": false,
      "is_shovel_official": false,
      "is_shovel_known": false
    },
    {
      "name": "Personal-Scoop-Bucket",
      "full_name": "kkkykin/Personal-Scoop-Bucket",
      "git_url": "https://github.com/kkkykin/Personal-Scoop-Bucket.git",
      "html_url": "https://github.com/kkkykin/Personal-Scoop-Bucket",
      "score": 1.0,
      "default_branch": "master",
      "topics": [],
      "last_checked": "2026-04-29T14:04:34Z",
      "pushed_at": "2026-04-27T21:30:31Z",
      "archived": false,
      "disabled": false,
      "entries": [
        "bucket/openjdk.json",
        "bucket/fingerprint-chromium.json",
        "bucket/browserpass.json",
        "bucket/ulister-tc.json",
        "bucket/sqlite-jdbc.json",
        "bucket/git-busybox.json",
        "bucket/webdav-tc.json",
        "bucket/fallout4-masterlist.json",
        "bucket/quicker.json",
        "bucket/bstweaker.json",
        "bucket/win-vind.json",
        "bucket/total7zip-tc.json",
        "bucket/bookxnote.json",
        "bucket/nscb.json",
        "bucket/odbc-tc.json",
        "bucket/cfst.json",
        "bucket/3proxy.json",
        "bucket/mcis.json",
        "bucket/sftp-tc.json",
        "bucket/brogue.json",
        "bucket/mingw-ucrt-winlibs.json",
        "bucket/skyrimse-masterlist.json",
        "bucket/sray.json",
        "bucket/burpsuite-np.json",
        "bucket/irfanview-tc.json",
        "bucket/surfingkeys-nvim.json",
        "bucket/llama-cpp-cuda.json",
        "bucket/sqlite-viewer-tc.json",
        "bucket/win-script-adv-tc.json",
        "bucket/mpv-v3.json",
        "bucket/sq.json",
        "bucket/tree-sitter-langs.json"
      ],
      "checkver_count": 32,
      "consecutive_failures": 6,
      "probe_success_rate": 1.0,
      "valid_probes": 3,
      "total_probes": 3,
      "unique_count": 30,
      "uniqueness_ratio": 0.9375,
      "auto_update_percentage": 100.0,
      "final_score": 136.9476134219972,
      "current_rank": 154,
      "rank_velocity": 1,
      "previous_rank": 154,
      "is_scoop_official": false,
      "is_scoop_known": false,
      "is_shovel_official": false,
      "is_shovel_known": false
    },
    {
      "name": "scoop-jp-fonts",
      "full_name": "ppyv/scoop-jp-fonts",
      "git_url": "https://github.com/ppyv/scoop-jp-fonts.git",
      "html_url": "https://github.com/ppyv/scoop-jp-fonts",
      "score": 1.0,
      "default_branch": "master",
      "topics": [
        "powershell",
        "scoop",
        "scoop-bucket"
      ],
      "last_checked": "2026-04-26T11:35:17Z",
      "pushed_at": "2026-02-25T06:09:28Z",
      "archived": false,
      "disabled": false,
      "entries": [
        "bucket/Explex-NF.json",
        "bucket/LINE-Seed.json",
        "bucket/Bizin-Gothic.json",
        "bucket/Moralerspace-JPDOC.json",
        "bucket/PlemolJP-HS.json",
        "bucket/Pending-Mono-NF.json",
        "bucket/Bizin-Gothic-NF.json",
        "bucket/Pending-Mono.json",
        "bucket/Firge.json",
        "bucket/NOTONOTO-HS.json",
        "bucket/Explex.json",
        "bucket/BIZTER.json",
        "bucket/PlemolJP.json",
        "bucket/Juisee.json",
        "bucket/Guguru-Sans-Code.json",
        "bucket/Pending-Mono-HW-JPDOC.json",
        "bucket/HackGen.json",
        "bucket/PlemolJP-NF.json",
        "bucket/Moralerspace-HW-JPDOC.json",
        "bucket/Juisee-NF.json",
        "bucket/Moralerspace-HW.json",
        "bucket/Moralerspace-HW-NF.json",
        "bucket/Moralerspace-NF.json",
        "bucket/Moralerspace.json",
        "bucket/Pending-Mono-JPDOC.json",
        "bucket/Firge-NF.json",
        "bucket/Bizin-Gothic-Discord.json",
        "bucket/NOTONOTO.json",
        "bucket/Pending-Mono-HW.json",
        "bucket/Pending-Mono-HW-NF.json",
        "bucket/UDEV-Gothic-NF.json",
        "bucket/HackGen-NF.json",
        "bucket/UDEV-Gothic.json"
      ],
      "checkver_count": 33,
      "consecutive_failures": 0,
      "probe_success_rate": 1.0,
      "valid_probes": 3,
      "total_probes": 3,
      "unique_count": 33,
      "uniqueness_ratio": 1.0,
      "auto_update_percentage": 100.0,
      "final_score": 136.7104763623931,
      "current_rank": 155,
      "rank_velocity": 1,
      "previous_rank": 155,
      "is_scoop_official": false,
      "is_scoop_known": false,
      "is_shovel_official": false,
      "is_shovel_known": false
    },
    {
      "name": "ScoopIt",
      "full_name": "mslxl/ScoopIt",
      "git_url": "https://github.com/mslxl/ScoopIt.git",
      "html_url": "https://github.com/mslxl/ScoopIt",
      "score": 1.0,
      "default_branch": "master",
      "topics": [
        "scoop",
        "scoop-apps",
        "scoop-bucket"
      ],
      "last_checked": "2026-04-29T15:06:11Z",
      "pushed_at": "2026-04-29T09:07:48Z",
      "archived": false,
      "disabled": false,
      "entries": [
        "bucket/font-otf-source-han-sans-hw-sc.json",
        "bucket/redpanda-cpp-mingw.json",
        "bucket/redpanda-cpp.json",
        "bucket/tai.json",
        "bucket/baidu-netdisk.json",
        "bucket/eudic-ting.json",
        "bucket/everything-cmdpal.json",
        "bucket/cf-tool.json",
        "bucket/peer-ban-helper-np.json",
        "bucket/dida365.json",
        "bucket/ammonite-scala3.2.json",
        "bucket/pot.json",
        "bucket/cpeditor.json",
        "bucket/kmonad-git.json",
        "bucket/feishu.json",
        "bucket/v-hub.json",
        "bucket/bilibili.json",
        "bucket/quicker-fast.json",
        "bucket/animeko.json",
        "bucket/maa-assistant-arknights.json",
        "bucket/youdao-dict-np.json",
        "bucket/moosync.json",
        "bucket/calibre-web.json",
        "bucket/nushell.json",
        "bucket/galaxy-buds-client.json",
        "bucket/ediary.json",
        "bucket/qianji.json",
        "bucket/rio-terminal.json",
        "bucket/iceda.json",
        "bucket/hmcl.json",
        "bucket/aslains-wows-modpack.json",
        "bucket/devcpporwell-mingw.json",
        "bucket/wemeet.json",
        "bucket/trzsz-ssh.json",
        "bucket/iceda-professional.json",
        "bucket/dingtalk.json"
      ],
      "checkver_count": 33,
      "consecutive_failures": 10,
      "probe_success_rate": 0.6666666666666666,
      "valid_probes": 2,
      "total_probes": 3,
      "unique_count": 34,
      "uniqueness_ratio": 0.9444444444444444,
      "auto_update_percentage": 91.67,
      "final_score": 136.66376868966336,
      "current_rank": 156,
      "rank_velocity": 1,
      "previous_rank": 156,
      "is_scoop_official": false,
      "is_scoop_known": false,
      "is_shovel_official": false,
      "is_shovel_known": false
    }
  ],
  "metadata": {
    "generated_at": "2026-04-29T19:55:52Z",
    "count": 5,
    "global_metrics": {
      "total_runs": 85,
      "total_run_time_seconds": 12826.174260616302,
      "total_repo_updates": 5440,
      "previous_total_buckets": 1233,
      "previous_total_recipes": 127569,
      "bucket_velocity": 0,
      "recipe_velocity": 0,
      "total_evictions": 0,
      "total_api_retries": 0,
      "last_run_discover_time": 0.0861368179321289,
      "last_run_update_time": 7.513004541397095,
      "ecosystem_reliability": 88.6,
      "cache_size_mb": 9.544140815734863,
      "total_unique_recipes": 31000,
      "auto_update_percentage": 85.35,
      "official_recipes": 48390,
      "community_recipes": 79179,
      "stale_buckets": 428,
      "shovel_buckets": 25,
      "scoop_buckets": 1208
    }
  }
}
