{
  "trending": [
    {
      "name": "scoop-zapps",
      "full_name": "kkzzhizhou/scoop-zapps",
      "git_url": "https://github.com/kkzzhizhou/scoop-zapps.git",
      "html_url": "https://github.com/kkzzhizhou/scoop-zapps",
      "score": 1.0,
      "default_branch": "master",
      "topics": [
        "excavator",
        "scoop",
        "scoop-apps",
        "scoop-bucket",
        "scoop-bucket-autoupdate"
      ],
      "last_checked": "2026-05-06T03:34:04Z",
      "pushed_at": "2026-05-05T02:01:50Z",
      "archived": false,
      "disabled": false,
      "entries": [
        "bucket/nmap.json",
        "bucket/lockhunter.json",
        "bucket/Notepad3-mod.json",
        "bucket/Proxifier.json",
        "bucket/SetUserFTA.json",
        "bucket/wps.json",
        "bucket/rustdesk.json",
        "bucket/Sandboxie-Classic.json",
        "bucket/officetool-dotnet.json",
        "bucket/Autoruns.json",
        "bucket/officetool.json",
        "bucket/Cache-Relocator.json",
        "bucket/electerm.json",
        "bucket/CompileAHK.json",
        "bucket/homedale.json",
        "bucket/coodesker.json",
        "bucket/WechatWork.json",
        "bucket/utorrent.json",
        "bucket/TwomonUSB.json",
        "bucket/googlechrome.json",
        "bucket/DingTalk.json",
        "bucket/TuBaTool.json",
        "bucket/BlueLifeHostsEditor.json",
        "bucket/linux-command.json",
        "bucket/termius.json",
        "bucket/sdkman.json",
        "bucket/ShadowsocksR.json",
        "bucket/QOwnNotes.json",
        "bucket/multimarkdown.json",
        "bucket/AutoHotkey.json",
        "bucket/Grub2.json",
        "bucket/tinyMediaManager.json",
        "bucket/chrome-with-flash.json",
        "bucket/WinSW.json"
      ],
      "checkver_count": 32,
      "consecutive_failures": 32,
      "probe_success_rate": 1.0,
      "valid_probes": 3,
      "total_probes": 3,
      "unique_count": 23,
      "uniqueness_ratio": 0.6764705882352942,
      "auto_update_percentage": 94.12,
      "final_score": 141.8302209223412,
      "current_rank": 144,
      "rank_velocity": 22,
      "previous_rank": 144,
      "is_scoop_official": false,
      "is_scoop_known": false,
      "is_shovel_official": false,
      "is_shovel_known": false
    },
    {
      "name": "scoop-personal",
      "full_name": "MagicalDrizzle/scoop-personal",
      "git_url": "https://github.com/MagicalDrizzle/scoop-personal.git",
      "html_url": "https://github.com/MagicalDrizzle/scoop-personal",
      "score": 1.0,
      "default_branch": "master",
      "topics": [
        "scoop-bucket"
      ],
      "last_checked": "2026-05-06T03:33:49Z",
      "pushed_at": "2026-05-04T14:30:54Z",
      "archived": false,
      "disabled": false,
      "entries": [
        "bucket/thtk-nightly.json",
        "bucket/winsetview.json",
        "bucket/vorbis-tools-chocobo1.json",
        "bucket/7-benchmark.json",
        "bucket/crystaldiskmark-aoi.json",
        "bucket/fancontrol-net48.json",
        "bucket/sizer4_archived.json",
        "bucket/opus-tools-chocobo1.json",
        "bucket/ascgen2.json",
        "bucket/antidupl.net-portable.json",
        "bucket/lolcrab.json",
        "bucket/dependency-runner.json",
        "bucket/gimagereader.json",
        "bucket/oggdec2.json",
        "bucket/ltfviewer.json",
        "bucket/crystaldiskinfo-aoi.json",
        "bucket/cotp.json",
        "bucket/notepad4.json",
        "bucket/openttd-jgrpp.json",
        "bucket/ldd-win.json",
        "bucket/mpv-git-zh.json",
        "bucket/yt-dlg.json",
        "bucket/pixiv-viewer.json",
        "bucket/binocle.json",
        "bucket/sizer3_archived.json",
        "bucket/diskus.json",
        "bucket/pixiv-viewer-electron.json",
        "bucket/reversion.json",
        "bucket/qbittorrent-lt20.json",
        "bucket/zadark.json",
        "bucket/browserouter.json",
        "bucket/dontsleep.json",
        "bucket/pdu.json"
      ],
      "checkver_count": 26,
      "consecutive_failures": 33,
      "probe_success_rate": 1.0,
      "valid_probes": 3,
      "total_probes": 3,
      "unique_count": 32,
      "uniqueness_ratio": 0.9696969696969697,
      "auto_update_percentage": 78.79,
      "final_score": 139.39540786924243,
      "current_rank": 154,
      "rank_velocity": 16,
      "previous_rank": 154,
      "is_scoop_official": false,
      "is_scoop_known": false,
      "is_shovel_official": false,
      "is_shovel_known": false
    },
    {
      "name": "Scoop-Python",
      "full_name": "TheRandomLabs/Scoop-Python",
      "git_url": "https://github.com/TheRandomLabs/Scoop-Python.git",
      "html_url": "https://github.com/TheRandomLabs/Scoop-Python",
      "score": 1.0,
      "default_branch": "master",
      "topics": [
        "python",
        "python-applications",
        "python-apps",
        "scoop",
        "scoop-apps",
        "scoop-bucket"
      ],
      "last_checked": "2026-05-06T03:33:58Z",
      "pushed_at": "2026-05-05T01:47:53Z",
      "archived": false,
      "disabled": false,
      "entries": [
        "bucket/pytest-py.json",
        "bucket/youtube-dl-py.json",
        "bucket/scdl-py.json",
        "bucket/ytmdl-py.json",
        "bucket/python-bucket-utils.json",
        "bucket/awscurl-py.json",
        "bucket/grip-py.json",
        "bucket/twine-py.json",
        "bucket/pip-py.json",
        "bucket/spotdl-py.json",
        "bucket/sphinx-py.json",
        "bucket/wheel-py.json",
        "bucket/codespell-py.json",
        "bucket/mypy-extensions-py.json",
        "bucket/pytube-py.json",
        "bucket/gitup-py.json",
        "bucket/httpie-py.json",
        "bucket/gallery-dl-py.json",
        "bucket/keyring-py.json",
        "bucket/virtualenv-py.json",
        "bucket/setuptools-py.json",
        "bucket/mypy-py.json",
        "bucket/rst-lint-py.json",
        "bucket/yapf-py.json",
        "bucket/http-prompt-py.json"
      ],
      "checkver_count": 25,
      "consecutive_failures": 22,
      "probe_success_rate": 1.0,
      "valid_probes": 3,
      "total_probes": 3,
      "unique_count": 25,
      "uniqueness_ratio": 1.0,
      "auto_update_percentage": 100.0,
      "final_score": 119.37144807032223,
      "current_rank": 184,
      "rank_velocity": 15,
      "previous_rank": 184,
      "is_scoop_official": false,
      "is_scoop_known": false,
      "is_shovel_official": false,
      "is_shovel_known": false
    },
    {
      "name": "scoop-bucket",
      "full_name": "bobo2334/scoop-bucket",
      "git_url": "https://github.com/bobo2334/scoop-bucket.git",
      "html_url": "https://github.com/bobo2334/scoop-bucket",
      "score": 1.0,
      "default_branch": "master",
      "topics": [
        "scoop-bucket"
      ],
      "last_checked": "2026-05-05T16:01:01Z",
      "pushed_at": "2026-04-30T04:09:22Z",
      "archived": false,
      "disabled": false,
      "entries": [
        "bucket/ark-server-manager.json",
        "bucket/chfs.json",
        "bucket/regester.json",
        "bucket/he3.json",
        "bucket/sockscap64.json",
        "bucket/hearthstone-deck-tracker.json",
        "bucket/ftp-rush.json",
        "bucket/ttime.json",
        "bucket/safeincloud.json",
        "bucket/apk-info.json",
        "bucket/watt-toolkit.json",
        "bucket/svu.json",
        "bucket/windows-update-blocker.json",
        "bucket/osfmount.json",
        "bucket/chiaki.json",
        "bucket/my-computer-manager.json",
        "bucket/nas-performance-tester.json",
        "bucket/windows-settings-blocker.json",
        "bucket/restic-browser.json"
      ],
      "checkver_count": 18,
      "consecutive_failures": 19,
      "probe_success_rate": 0.6666666666666666,
      "valid_probes": 2,
      "total_probes": 3,
      "unique_count": 18,
      "uniqueness_ratio": 0.9473684210526315,
      "auto_update_percentage": 94.74,
      "final_score": 93.43598410330986,
      "current_rank": 240,
      "rank_velocity": 3,
      "previous_rank": 240,
      "is_scoop_official": false,
      "is_scoop_known": false,
      "is_shovel_official": false,
      "is_shovel_known": false
    },
    {
      "name": "apps",
      "full_name": "Dott-rus/apps",
      "git_url": "https://github.com/Dott-rus/apps.git",
      "html_url": "https://github.com/Dott-rus/apps",
      "score": 1.0,
      "default_branch": "master",
      "topics": [
        "scoop",
        "scoop-bucket"
      ],
      "last_checked": "2026-05-05T16:01:06Z",
      "pushed_at": "2026-04-27T17:45:53Z",
      "archived": false,
      "disabled": false,
      "entries": [
        "bucket/kanata.json",
        "bucket/obsidian.json",
        "bucket/fastfetch.json",
        "bucket/tagstudio.json",
        "bucket/ss.json",
        "bucket/ayugram.json",
        "bucket/kanata_winIOv2.json",
        "bucket/keep-alive.json",
        "bucket/mpv.json",
        "bucket/lf.json",
        "bucket/keepassxc.json",
        "bucket/sudo.json",
        "bucket/opentabletdriver.json",
        "bucket/musicbee.json",
        "bucket/neovim.json",
        "bucket/scrcpy.json",
        "bucket/7zip.json",
        "bucket/everything.json",
        "bucket/zoxide.json"
      ],
      "checkver_count": 19,
      "consecutive_failures": 19,
      "probe_success_rate": 0.6666666666666666,
      "valid_probes": 2,
      "total_probes": 3,
      "unique_count": 4,
      "uniqueness_ratio": 0.21052631578947367,
      "auto_update_percentage": 100.0,
      "final_score": 93.43598410330986,
      "current_rank": 241,
      "rank_velocity": 3,
      "previous_rank": 241,
      "is_scoop_official": false,
      "is_scoop_known": false,
      "is_shovel_official": false,
      "is_shovel_known": false
    }
  ],
  "metadata": {
    "generated_at": "2026-05-06T03:34:09Z",
    "count": 5,
    "global_metrics": {
      "total_runs": 223,
      "total_run_time_seconds": 37196.78421831131,
      "total_repo_updates": 13915,
      "previous_total_buckets": 1257,
      "previous_total_recipes": 127748,
      "bucket_velocity": 0,
      "recipe_velocity": 0,
      "total_evictions": 0,
      "total_api_retries": 0,
      "last_run_discover_time": 3.1055150032043457,
      "last_run_update_time": 25.068394899368286,
      "ecosystem_reliability": 88.4,
      "cache_size_mb": 9.573718070983887,
      "total_unique_recipes": 31039,
      "auto_update_percentage": 85.36,
      "official_recipes": 48436,
      "community_recipes": 79312,
      "stale_buckets": 433,
      "shovel_buckets": 25,
      "scoop_buckets": 1232
    }
  }
}
