{
  "trending": [],
  "metadata": {
    "generated_at": "2026-04-26T19:38:27Z",
    "count": 0,
    "global_metrics": {
      "total_runs": 16,
      "total_run_time_seconds": 50.803853034973145,
      "total_repo_updates": 972,
      "previous_total_buckets": 224,
      "previous_total_recipes": 3133,
      "bucket_velocity": 2,
      "recipe_velocity": 11,
      "total_evictions": 0,
      "total_api_retries": 0,
      "last_run_discover_time": 3.177891969680786,
      "last_run_update_time": 2.0636088848114014,
      "ecosystem_reliability": 100.0,
      "cache_size_mb": 0.5624809265136719,
      "total_unique_recipes": 2784,
      "auto_update_percentage": 36.1,
      "official_recipes": 364,
      "community_recipes": 2769,
      "stale_buckets": 121,
      "shovel_buckets": 0,
      "scoop_buckets": 224
    }
  }
}
